mpi4pytools-0.2.0.dist-info/licenses/LICENSE
mpitools/__init__.py
mpitools/base.py
mpitools/divide_work.py
mpitools/comms/__init__.py
mpitools/comms/buffered_collective.py
mpitools/comms/buffered_reduction.py
mpitools/comms/collective.py
mpitools/comms/reduction.py
mpitools/comms/utils.py
mpitools/comms/variable_collective.py
mpitools/queue/__init__.py
mpitools/queue/managers.py
mpitools/queue/tasks.py
mpi4pytools-0.2.0.dist-info/METADATA
mpi4pytools-0.2.0.dist-info/WHEEL
mpi4pytools-0.2.0.dist-info/top_level.txt
mpi4pytools-0.2.0.dist-info/RECORD
