Metadata-Version: 2.4
Name: mpi4pytools
Version: 0.2.0
Summary: Simple decorators and utilities for MPI parallel computing
Author-email: "Erik A. Bensen" <erik-a-bensen@users.noreply.github.com>
License: MIT
Project-URL: Homepage, https://github.com/erik-a-bensen/mpitools
Project-URL: Documentation, https://github.com/erik-a-bensen/mpitools/blob/main/API_DOCS.md
Project-URL: Repository, https://github.com/erik-a-bensen/mpitools
Project-URL: Issues, https://github.com/erik-a-bensen/mpitools/issues
Keywords: mpi,parallel,computing,decorators,hpc
Classifier: Development Status :: 3 - Alpha
Classifier: Intended Audience :: Developers
Classifier: Intended Audience :: Science/Research
Classifier: License :: OSI Approved :: MIT License
Classifier: Programming Language :: Python :: 3
Classifier: Programming Language :: Python :: 3.8
Classifier: Programming Language :: Python :: 3.9
Classifier: Programming Language :: Python :: 3.10
Classifier: Programming Language :: Python :: 3.11
Classifier: Programming Language :: Python :: 3.12
Classifier: Topic :: Scientific/Engineering
Classifier: Topic :: System :: Distributed Computing
Requires-Python: >=3.8
License-File: LICENSE
Requires-Dist: numpy
Requires-Dist: mpi4py
Dynamic: license-file
